overlap-0.2.0.dist-info/RECORD
overlap-0.2.0.dist-info/WHEEL
overlap-0.2.0.dist-info/METADATA
overlap-0.2.0.dist-info/licenses/LICENSE
overlap/_version.py
overlap/__init__.py
overlap/_overlap.cpython-310-darwin.so
