Metadata-Version: 2.2
Name: overlap
Version: 0.2.0
Summary: Exact calculation of the overlap volume and area of spheres and mesh elements
Keywords: computational-geometry,mesh-processing,numerical-simulations
Author-Email: Severin Strobl <git@severin-strobl.de>
License: MIT
Classifier: Programming Language :: Python :: 3 :: Only
Classifier: Programming Language :: Python :: 3.9
Classifier: Programming Language :: Python :: 3.10
Classifier: Programming Language :: Python :: 3.11
Classifier: Programming Language :: Python :: 3.12
Classifier: Programming Language :: Python :: 3.13
Classifier: Topic :: Scientific/Engineering
Project-URL: github, https://github.com/severinstrobl/overlap
Project-URL: issues, https://github.com/severinstrobl/overlap/issues
Project-URL: source, https://github.com/severinstrobl/overlap.git
Requires-Python: >=3.9
Requires-Dist: numpy
Provides-Extra: test
Requires-Dist: pytest>=6; extra == "test"
